markdown_gfm_admonition.py
markdown_gfm_admonition-0.1.1.dist-info/LICENSE
markdown_gfm_admonition-0.1.1.dist-info/METADATA
markdown_gfm_admonition-0.1.1.dist-info/WHEEL
markdown_gfm_admonition-0.1.1.dist-info/entry_points.txt
markdown_gfm_admonition-0.1.1.dist-info/top_level.txt
markdown_gfm_admonition-0.1.1.dist-info/RECORD
